RTL/size_checker.v
/************************************************
BSD 3-Clause License

Copyright (c) 2019, HPCN Group, UAM Spain (hpcn-uam.es)
and Systems Group, ETH Zurich (systems.ethz.ch)
All rights reserved.


Redistribution and use in source and binary forms, with or without
modification, are permitted provided that the following conditions are met:

* Redistributions of source code must retain the above copyright notice, this
  list of conditions and the following disclaimer.

* Redistributions in binary form must reproduce the above copyright notice,
  this list of conditions and the following disclaimer in the documentation
  and/or other materials provided with the distribution.

* Neither the name of the copyright holder nor the names of its
  contributors may be used to endorse or promote products derived from
  this software without specific prior written permission.

THIS SOFTWARE IS PROVIDED BY THE COPYRIGHT HOLDERS AND CONTRIBUTORS "AS IS"
AND ANY EXPRESS OR IMPLIED WARRANTIES, INCLUDING, BUT NOT LIMITED TO, THE
IMPLIED WARRANTIES OF MERCHANTABILITY AND FITNESS FOR A PARTICULAR PURPOSE ARE
DISCLAIMED. IN NO EVENT SHALL THE COPYRIGHT HOLDER OR CONTRIBUTORS BE LIABLE
FOR ANY DIRECT, INDIRECT, INCIDENTAL, SPECIAL, EXEMPLARY, OR CONSEQUENTIAL
DAMAGES (INCLUDING, BUT NOT LIMITED TO, PROCUREMENT OF SUBSTITUTE GOODS OR
SERVICES; LOSS OF USE, DATA, OR PROFITS; OR BUSINESS INTERRUPTION) HOWEVER
CAUSED AND ON ANY THEORY OF LIABILITY, WHETHER IN CONTRACT, STRICT LIABILITY,
OR TORT (INCLUDING NEGLIGENCE OR OTHERWISE) ARISING IN ANY WAY OUT OF THE USE
OF THIS SOFTWARE, EVEN IF ADVISED OF THE POSSIBILITY OF SUCH DAMAGE.

************************************************/


//  Description   : This Module completes the packet to 60 bytes when the packets are smaller than 60 bytes

`timescale 1ns/1ps

module size_checker#
    (
        // Width of S_AXI data bus
        parameter C_AXIS_DATA_WIDTH             = 512,
        parameter TUSER_WIDTH                   =  1,
        parameter TDEST_WIDTH                   =  1

    )
    (
      (* X_INTERFACE_INFO = "xilinx.com:signal:clock:1.0 CLK CLK" *)
      (* X_INTERFACE_PARAMETER = "ASSOCIATED_BUSIF S_AXIS:M_AXIS, ASSOCIATED_RESET RST_N" *)
      input  wire                      CLK            ,
      (* X_INTERFACE_INFO = "xilinx.com:signal:reset:1.0 RST_N RST" *)
      (* X_INTERFACE_PARAMETER = "POLARITY ACTIVE_LOW" *)
      input  wire                      RST_N          ,
    
      (* X_INTERFACE_INFO = "xilinx.com:interface:axis:1.0 S_AXIS TDATA" *)  
      input  wire              [511:0] S_AXIS_TDATA   ,
      (* X_INTERFACE_INFO = "xilinx.com:interface:axis:1.0 S_AXIS TKEEP" *)
      input  wire               [63:0] S_AXIS_TKEEP   ,
      (* X_INTERFACE_INFO = "xilinx.com:interface:axis:1.0 S_AXIS TLAST" *) 
      input  wire                      S_AXIS_TLAST   ,
      (* X_INTERFACE_INFO = "xilinx.com:interface:axis:1.0 S_AXIS TVALID" *) 
      input  wire                      S_AXIS_TVALID  ,
      (* X_INTERFACE_INFO = "xilinx.com:interface:axis:1.0 S_AXIS TDEST" *) 
      input  wire  [TDEST_WIDTH-1 : 0] S_AXIS_TDEST   ,
      (* X_INTERFACE_INFO = "xilinx.com:interface:axis:1.0 S_AXIS TUSER" *) 
      input  wire  [TUSER_WIDTH-1 : 0] S_AXIS_TUSER   ,
      (* X_INTERFACE_INFO = "xilinx.com:interface:axis:1.0 S_AXIS TREADY" *) 
      output wire                      S_AXIS_TREADY  ,

      (* X_INTERFACE_INFO = "xilinx.com:interface:axis:1.0 M_AXIS TDATA" *)   
      output reg               [511:0] M_AXIS_TDATA   ,
      (* X_INTERFACE_INFO = "xilinx.com:interface:axis:1.0 M_AXIS TKEEP" *)
      output reg                [63:0] M_AXIS_TKEEP   ,
      (* X_INTERFACE_INFO = "xilinx.com:interface:axis:1.0 M_AXIS TLAST" *)
      output reg                       M_AXIS_TLAST   ,
      (* X_INTERFACE_INFO = "xilinx.com:interface:axis:1.0 M_AXIS TVALID" *)
      output reg                       M_AXIS_TVALID  ,
      (* X_INTERFACE_INFO = "xilinx.com:interface:axis:1.0 M_AXIS TDEST" *) 
      output reg   [TDEST_WIDTH-1 : 0] M_AXIS_TDEST   ,
      (* X_INTERFACE_INFO = "xilinx.com:interface:axis:1.0 M_AXIS TUSER" *)
      output reg   [TUSER_WIDTH-1 : 0] M_AXIS_TUSER   ,
      (* X_INTERFACE_INFO = "xilinx.com:interface:axis:1.0 M_AXIS TREADY" *)
      input  wire                      M_AXIS_TREADY 

);

  reg     first_transaction= 1'b1;

  assign  S_AXIS_TREADY = M_AXIS_TREADY;

  always @(*) begin
    M_AXIS_TDATA      <= S_AXIS_TDATA;    
    M_AXIS_TKEEP      <= S_AXIS_TKEEP;    
    M_AXIS_TLAST      <= S_AXIS_TLAST;    
    M_AXIS_TVALID     <= S_AXIS_TVALID;    
    M_AXIS_TDEST      <= S_AXIS_TDEST;    
    M_AXIS_TUSER      <= S_AXIS_TUSER;          

    if (S_AXIS_TVALID && S_AXIS_TLAST) begin                          // one-transaction packet
      if (first_transaction && ~S_AXIS_TKEEP[59]) begin
        M_AXIS_TKEEP    <= {4'd0,{60{1'b1}}};                         // complete packet to the minimum size (60 bytes)
      end
    end
  end


  always @(posedge CLK) begin
    if (~RST_N) begin
      first_transaction   <= 1'b1;
    end
    else begin
      if (S_AXIS_TVALID && S_AXIS_TREADY) begin                         // when a valid transaction is active tie low flag
        first_transaction   <= 1'b0;
      end

      if (S_AXIS_TVALID && S_AXIS_TREADY && S_AXIS_TLAST) begin         // one-transaction packet
        first_transaction <= 1'b1;                                      // Asserting flag with the last transaction of a packet (it could be one-transaction packet)
      end
    end
  end

endmodule

tests/size_checker_backpressure_tb.sv
`timescale 1ns/1ps

module size_checker_backpressure_tb;
  reg clk = 1'b0;
  reg rst_n = 1'b0;

  reg [511:0] s_axis_tdata = '0;
  reg [63:0] s_axis_tkeep = '0;
  reg s_axis_tlast = 1'b0;
  reg s_axis_tvalid = 1'b0;
  reg s_axis_tdest = 1'b0;
  reg s_axis_tuser = 1'b0;
  wire s_axis_tready;

  wire [511:0] m_axis_tdata;
  wire [63:0] m_axis_tkeep;
  wire m_axis_tlast;
  wire m_axis_tvalid;
  wire m_axis_tdest;
  wire m_axis_tuser;
  reg m_axis_tready = 1'b0;

  reg [579:0] stalled_payload;
  integer beat_id = 0;

  always #5 clk = ~clk;

  size_checker dut (
    .CLK(clk),
    .RST_N(rst_n),
    .S_AXIS_TDATA(s_axis_tdata),
    .S_AXIS_TKEEP(s_axis_tkeep),
    .S_AXIS_TLAST(s_axis_tlast),
    .S_AXIS_TVALID(s_axis_tvalid),
    .S_AXIS_TDEST(s_axis_tdest),
    .S_AXIS_TUSER(s_axis_tuser),
    .S_AXIS_TREADY(s_axis_tready),
    .M_AXIS_TDATA(m_axis_tdata),
    .M_AXIS_TKEEP(m_axis_tkeep),
    .M_AXIS_TLAST(m_axis_tlast),
    .M_AXIS_TVALID(m_axis_tvalid),
    .M_AXIS_TDEST(m_axis_tdest),
    .M_AXIS_TUSER(m_axis_tuser),
    .M_AXIS_TREADY(m_axis_tready)
  );

  function automatic [579:0] output_payload;
    output_payload = {
      m_axis_tdata,
      m_axis_tkeep,
      m_axis_tlast,
      m_axis_tvalid,
      m_axis_tdest,
      m_axis_tuser
    };
  endfunction

  function automatic [63:0] keep_mask(input integer byte_count);
    begin
      if (byte_count == 64)
        keep_mask = {64{1'b1}};
      else
        keep_mask = (64'b1 << byte_count) - 1'b1;
    end
  endfunction

  task automatic send_beat(
    input integer valid_bytes,
    input reg last,
    input integer stall_cycles,
    input [63:0] expected_keep
  );
    integer cycle;
    begin
      @(negedge clk);
      s_axis_tdata = {448'b0, beat_id[31:0], valid_bytes[15:0], stall_cycles[15:0]};
      s_axis_tkeep = keep_mask(valid_bytes);
      s_axis_tlast = last;
      s_axis_tvalid = 1'b1;
      m_axis_tready = (stall_cycles == 0);
      #1;

      if (!m_axis_tvalid || m_axis_tkeep !== expected_keep)
        $fatal(1, "unexpected output mask for %0d-byte beat", valid_bytes);
      if (m_axis_tdata !== s_axis_tdata || m_axis_tlast !== last)
        $fatal(1, "output payload does not match the input beat");
      stalled_payload = output_payload();

      for (cycle = 0; cycle < stall_cycles; cycle = cycle + 1) begin
        @(posedge clk);
        #1;
        if (output_payload() !== stalled_payload)
          $fatal(1, "AXI output changed during stall cycle %0d", cycle);
      end

      if (stall_cycles != 0) begin
        @(negedge clk);
        m_axis_tready = 1'b1;
        #1;
        if (output_payload() !== stalled_payload)
          $fatal(1, "AXI output changed when TREADY was released");
      end

      @(posedge clk);
      @(negedge clk);
      s_axis_tvalid = 1'b0;
      s_axis_tlast = 1'b0;
      beat_id = beat_id + 1;
    end
  endtask

  task automatic send_packet(input integer byte_count, input integer stall_cycles);
    integer remaining;
    integer beat_bytes;
    begin
      remaining = byte_count;
      while (remaining > 64) begin
        send_beat(64, 1'b0, 0, keep_mask(64));
        remaining = remaining - 64;
      end

      beat_bytes = remaining;
      if (byte_count < 60)
        send_beat(beat_bytes, 1'b1, stall_cycles, keep_mask(60));
      else
        send_beat(beat_bytes, 1'b1, stall_cycles, keep_mask(beat_bytes));

      @(posedge clk);
    end
  endtask

  initial begin
    $dumpfile("size_checker_backpressure.vcd");
    $dumpvars(0, size_checker_backpressure_tb);

    repeat (2) @(posedge clk);
    @(negedge clk);
    rst_n = 1'b1;

    s_axis_tdest = 1'b1;
    s_axis_tuser = 1'b1;

    send_packet(60, 0);
    send_packet(62, 0);
    send_packet(50, 0);
    send_packet(133, 0);

    send_packet(60, 1);
    send_packet(62, 1);
    send_packet(50, 1);
    send_packet(133, 1);

    send_packet(60, 3);
    send_packet(62, 3);
    send_packet(50, 3);
    send_packet(133, 3);

    $display("PASS: all 12 size and backpressure cases are stable");
    $finish;
  end
endmodule

tests/size_checker_backpressure.vcd
$date
	Thu Aug 27 19:42:15 2026
$end
$version
	Icarus Verilog
$end
$timescale
	1ps
$end
$scope module size_checker_backpressure_tb $end
$var wire 1 ! s_axis_tready $end
$var wire 1 " m_axis_tvalid $end
$var wire 1 # m_axis_tuser $end
$var wire 1 $ m_axis_tlast $end
$var wire 64 % m_axis_tkeep [63:0] $end
$var wire 1 & m_axis_tdest $end
$var wire 512 ' m_axis_tdata [511:0] $end
$var reg 1 ( clk $end
$var reg 1 ) m_axis_tready $end
$var reg 1 * rst_n $end
$var reg 512 + s_axis_tdata [511:0] $end
$var reg 1 , s_axis_tdest $end
$var reg 64 - s_axis_tkeep [63:0] $end
$var reg 1 . s_axis_tlast $end
$var reg 1 / s_axis_tuser $end
$var reg 1 0 s_axis_tvalid $end
$var reg 580 1 stalled_payload [579:0] $end
$var integer 32 2 beat_id [31:0] $end
$scope function keep_mask $end
$upscope $end
$scope function output_payload $end
$upscope $end
$scope module dut $end
$var wire 1 ( CLK $end
$var wire 1 ) M_AXIS_TREADY $end
$var wire 1 * RST_N $end
$var wire 512 3 S_AXIS_TDATA [511:0] $end
$var wire 1 , S_AXIS_TDEST $end
$var wire 64 4 S_AXIS_TKEEP [63:0] $end
$var wire 1 . S_AXIS_TLAST $end
$var wire 1 ! S_AXIS_TREADY $end
$var wire 1 / S_AXIS_TUSER $end
$var wire 1 0 S_AXIS_TVALID $end
$var parameter 32 5 C_AXIS_DATA_WIDTH $end
$var parameter 32 6 TDEST_WIDTH $end
$var parameter 32 7 TUSER_WIDTH $end
$var reg 512 8 M_AXIS_TDATA [511:0] $end
$var reg 1 & M_AXIS_TDEST $end
$var reg 64 9 M_AXIS_TKEEP [63:0] $end
$var reg 1 $ M_AXIS_TLAST $end
$var reg 1 # M_AXIS_TUSER $end
$var reg 1 " M_AXIS_TVALID $end
$var reg 1 : first_transaction $end
$upscope $end
$scope task send_beat $end
$upscope $end
$scope task send_packet $end
$upscope $end
$upscope $end
$enddefinitions $end
$comment Show the parameter values. $end
$dumpall
b1 7
b1 6
b1000000000 5
$end
#0
$dumpvars
1:
bx 9
bx 8
b0 4
b0 3
b0 2
bx 1
00
0/
0.
b0 -
0,
b0 +
0*
0)
0(
bx '
x&
bx %
x$
x#
x"
0!
$end
#5000
1(
#10000
0(
#15000
1(
#20000
1#
1&
0"
0$
b0 %
b0 9
b0 '
b0 8
1/
1,
1*
0(
#25000
1(
#30000
1"
1$
b111111111111111111111111111111111111111111111111111111111111 %
b111111111111111111111111111111111111111111111111111111111111 9
b1111000000000000000000 '
b1111000000000000000000 8
1!
1)
10
1.
b111111111111111111111111111111111111111111111111111111111111 -
b111111111111111111111111111111111111111111111111111111111111 4
b1111000000000000000000 +
b1111000000000000000000 3
0(
#31000
b111100000000000000000000001111111111111111111111111111111111111111111111111111111111111111 1
#35000
1:
1(
#40000
0"
0$
b1 2
0.
00
0(
#45000
1(
#50000
1"
1$
b11111111111111111111111111111111111111111111111111111111111111 %
b11111111111111111111111111111111111111111111111111111111111111 9
b100000000001111100000000000000000 '
b100000000001111100000000000000000 8
10
1.
b11111111111111111111111111111111111111111111111111111111111111 -
b11111111111111111111111111111111111111111111111111111111111111 4
b100000000001111100000000000000000 +
b100000000001111100000000000000000 3
0(
#51000
b10000000000111110000000000000000000111111111111111111111111111111111111111111111111111111111111111111 1
#55000
1:
1(
#60000
0"
0$
b10 2
0.
00
0(
#65000
1(
#70000
1"
1$
b111111111111111111111111111111111111111111111111111111111111 %
b111111111111111111111111111111111111111111111111111111111111 9
b1000000000001100100000000000000000 '
b1000000000001100100000000000000000 8
10
1.
b11111111111111111111111111111111111111111111111111 -
b11111111111111111111111111111111111111111111111111 4
b1000000000001100100000000000000000 +
b1000000000001100100000000000000000 3
0(
#71000
b100000000000110010000000000000000000001111111111111111111111111111111111111111111111111111111111111111 1
#75000
b111111111111111111111111111111111111111111111111111111111111 %
b111111111111111111111111111111111111111111111111111111111111 9
1:
1(
#80000
0"
0$
b11111111111111111111111111111111111111111111111111 %
b11111111111111111111111111111111111111111111111111 9
b11 2
0.
00
0(
#85000
1(
#90000
1"
b1111111111111111111111111111111111111111111111111111111111111111 %
b1111111111111111111111111111111111111111111111111111111111111111 9
b1100000000010000000000000000000000 '
b1100000000010000000000000000000000 8
10
b1111111111111111111111111111111111111111111111111111111111111111 -
b1111111111111111111111111111111111111111111111111111111111111111 4
b1100000000010000000000000000000000 +
b1100000000010000000000000000000000 3
0(
#91000
b110000000001000000000000000000000011111111111111111111111111111111111111111111111111111111111111110111 1
#95000
0:
1(
#100000
0"
b100 2
00
0(
#105000
1(
#110000
1"
b10000000000010000000000000000000000 '
b10000000000010000000000000000000000 8
10
b10000000000010000000000000000000000 +
b10000000000010000000000000000000000 3
0(
#111000
b1000000000001000000000000000000000011111111111111111111111111111111111111111111111111111111111111110111 1
#115000
1(
#120000
0"
b101 2
00
0(
#125000
1(
#130000
1"
1$
b11111 %
b11111 9
b10100000000000001010000000000000000 '
b10100000000000001010000000000000000 8
10
1.
b11111 -
b11111 4
b10100000000000001010000000000000000 +
b10100000000000001010000000000000000 3
0(
#131000
b1010000000000000101000000000000000000000000000000000000000000000000000000000000000000000000000111111111 1
#135000
b111111111111111111111111111111111111111111111111111111111111 %
b111111111111111111111111111111111111111111111111111111111111 9
1:
1(
#140000
0"
0$
b11111 %
b11111 9
b110 2
0.
00
0(
#145000
1(
#150000
1"
1$
b111111111111111111111111111111111111111111111111111111111111 %
b111111111111111111111111111111111111111111111111111111111111 9
b11000000000001111000000000000000001 '
b11000000000001111000000000000000001 8
0!
0)
10
1.
b111111111111111111111111111111111111111111111111111111111111 -
b111111111111111111111111111111111111111111111111111111111111 4
b11000000000001111000000000000000001 +
b11000000000001111000000000000000001 3
0(
#151000
b1100000000000111100000000000000000100001111111111111111111111111111111111111111111111111111111111111111 1
#155000
1(
#160000
1!
1)
0(
#165000
1:
1(
#170000
0"
0$
b111 2
0.
00
0(
#175000
1(
#180000
1"
1$
b11111111111111111111111111111111111111111111111111111111111111 %
b11111111111111111111111111111111111111111111111111111111111111 9
b11100000000001111100000000000000001 '
b11100000000001111100000000000000001 8
0!
0)
10
1.
b11111111111111111111111111111111111111111111111111111111111111 -
b11111111111111111111111111111111111111111111111111111111111111 4
b11100000000001111100000000000000001 +
b11100000000001111100000000000000001 3
0(
#181000
b1110000000000111110000000000000000100111111111111111111111111111111111111111111111111111111111111111111 1
#185000
1(
#190000
1!
1)
0(
#195000
1:
1(
#200000
0"
0$
b1000 2
0.
00
0(
#205000
1(
#210000
1"
1$
b111111111111111111111111111111111111111111111111111111111111 %
b111111111111111111111111111111111111111111111111111111111111 9
b100000000000001100100000000000000001 '
b100000000000001100100000000000000001 8
0!
0)
10
1.
b11111111111111111111111111111111111111111111111111 -
b11111111111111111111111111111111111111111111111111 4
b100000000000001100100000000000000001 +
b100000000000001100100000000000000001 3
0(
#211000
b10000000000000110010000000000000000100001111111111111111111111111111111111111111111111111111111111111111 1
#215000
1(
#220000
1!
1)
0(
#225000
b111111111111111111111111111111111111111111111111111111111111 %
b111111111111111111111111111111111111111111111111111111111111 9
1:
1(
#230000
0"
0$
b11111111111111111111111111111111111111111111111111 %
b11111111111111111111111111111111111111111111111111 9
b1001 2
0.
00
0(
#235000
1(
#240000
1"
b1111111111111111111111111111111111111111111111111111111111111111 %
b1111111111111111111111111111111111111111111111111111111111111111 9
b100100000000010000000000000000000000 '
b100100000000010000000000000000000000 8
10
b1111111111111111111111111111111111111111111111111111111111111111 -
b1111111111111111111111111111111111111111111111111111111111111111 4
b100100000000010000000000000000000000 +
b100100000000010000000000000000000000 3
0(
#241000
b10010000000001000000000000000000000011111111111111111111111111111111111111111111111111111111111111110111 1
#245000
0:
1(
#250000
0"
b1010 2
00
0(
#255000
1(
#260000
1"
b101000000000010000000000000000000000 '
b101000000000010000000000000000000000 8
10
b101000000000010000000000000000000000 +
b101000000000010000000000000000000000 3
0(
#261000
b10100000000001000000000000000000000011111111111111111111111111111111111111111111111111111111111111110111 1
#265000
1(
#270000
0"
b1011 2
00
0(
#275000
1(
#280000
1"
1$
b11111 %
b11111 9
b101100000000000001010000000000000001 '
b101100000000000001010000000000000001 8
0!
0)
10
1.
b11111 -
b11111 4
b101100000000000001010000000000000001 +
b101100000000000001010000000000000001 3
0(
#281000
b10110000000000000101000000000000000100000000000000000000000000000000000000000000000000000000000111111111 1
#285000
1(
#290000
1!
1)
0(
#295000
b111111111111111111111111111111111111111111111111111111111111 %
b111111111111111111111111111111111111111111111111111111111111 9
1:
1(
#300000
0"
0$
b11111 %
b11111 9
b1100 2
0.
00
0(
#305000
1(
#310000
1"
1$
b111111111111111111111111111111111111111111111111111111111111 %
b111111111111111111111111111111111111111111111111111111111111 9
b110000000000001111000000000000000011 '
b110000000000001111000000000000000011 8
0!
0)
10
1.
b111111111111111111111111111111111111111111111111111111111111 -
b111111111111111111111111111111111111111111111111111111111111 4
b110000000000001111000000000000000011 +
b110000000000001111000000000000000011 3
0(
#311000
b11000000000000111100000000000000001100001111111111111111111111111111111111111111111111111111111111111111 1
#315000
1(
#320000
0(
#325000
1(
#330000
0(
#335000
1(
#340000
1!
1)
0(
#345000
1:
1(
#350000
0"
0$
b1101 2
0.
00
0(
#355000
1(
#360000
1"
1$
b11111111111111111111111111111111111111111111111111111111111111 %
b11111111111111111111111111111111111111111111111111111111111111 9
b110100000000001111100000000000000011 '
b110100000000001111100000000000000011 8
0!
0)
10
1.
b11111111111111111111111111111111111111111111111111111111111111 -
b11111111111111111111111111111111111111111111111111111111111111 4
b110100000000001111100000000000000011 +
b110100000000001111100000000000000011 3
0(
#361000
b11010000000000111110000000000000001100111111111111111111111111111111111111111111111111111111111111111111 1
#365000
1(
#370000
0(
#375000
1(
#380000
0(
#385000
1(
#390000
1!
1)
0(
#395000
1:
1(
#400000
0"
0$
b1110 2
0.
00
0(
#405000
1(
#410000
1"
1$
b111111111111111111111111111111111111111111111111111111111111 %
b111111111111111111111111111111111111111111111111111111111111 9
b111000000000001100100000000000000011 '
b111000000000001100100000000000000011 8
0!
0)
10
1.
b11111111111111111111111111111111111111111111111111 -
b11111111111111111111111111111111111111111111111111 4
b111000000000001100100000000000000011 +
b111000000000001100100000000000000011 3
0(
#411000
b11100000000000110010000000000000001100001111111111111111111111111111111111111111111111111111111111111111 1
#415000
1(
#420000
0(
#425000
1(
#430000
0(
#435000
1(
#440000
1!
1)
0(
#445000
b111111111111111111111111111111111111111111111111111111111111 %
b111111111111111111111111111111111111111111111111111111111111 9
1:
1(
#450000
0"
0$
b11111111111111111111111111111111111111111111111111 %
b11111111111111111111111111111111111111111111111111 9
b1111 2
0.
00
0(
#455000
1(
#460000
1"
b1111111111111111111111111111111111111111111111111111111111111111 %
b1111111111111111111111111111111111111111111111111111111111111111 9
b111100000000010000000000000000000000 '
b111100000000010000000000000000000000 8
10
b1111111111111111111111111111111111111111111111111111111111111111 -
b1111111111111111111111111111111111111111111111111111111111111111 4
b111100000000010000000000000000000000 +
b111100000000010000000000000000000000 3
0(
#461000
b11110000000001000000000000000000000011111111111111111111111111111111111111111111111111111111111111110111 1
#465000
0:
1(
#470000
0"
b10000 2
00
0(
#475000
1(
#480000
1"
b1000000000000010000000000000000000000 '
b1000000000000010000000000000000000000 8
10
b1000000000000010000000000000000000000 +
b1000000000000010000000000000000000000 3
0(
#481000
b100000000000001000000000000000000000011111111111111111111111111111111111111111111111111111111111111110111 1
#485000
1(
#490000
0"
b10001 2
00
0(
#495000
1(
#500000
1"
1$
b11111 %
b11111 9
b1000100000000000001010000000000000011 '
b1000100000000000001010000000000000011 8
0!
0)
10
1.
b11111 -
b11111 4
b1000100000000000001010000000000000011 +
b1000100000000000001010000000000000011 3
0(
#501000
b100010000000000000101000000000000001100000000000000000000000000000000000000000000000000000000000111111111 1
#505000
1(
#510000
0(
#515000
1(
#520000
0(
#525000
1(
#530000
1!
1)
0(
#535000
b111111111111111111111111111111111111111111111111111111111111 %
b111111111111111111111111111111111111111111111111111111111111 9
1:
1(
#540000
0"
0$
b11111 %
b11111 9
b10010 2
0.
00
0(
