RTL/size_checker.v
/************************************************
BSD 3-Clause License

Copyright (c) 2019, HPCN Group, UAM Spain (hpcn-uam.es)
and Systems Group, ETH Zurich (systems.ethz.ch)
All rights reserved.


Redistribution and use in source and binary forms, with or without
modification, are permitted provided that the following conditions are met:

* Redistributions of source code must retain the above copyright notice, this
  list of conditions and the following disclaimer.

* Redistributions in binary form must reproduce the above copyright notice,
  this list of conditions and the following disclaimer in the documentation
  and/or other materials provided with the distribution.

* Neither the name of the copyright holder nor the names of its
  contributors may be used to endorse or promote products derived from
  this software without specific prior written permission.

THIS SOFTWARE IS PROVIDED BY THE COPYRIGHT HOLDERS AND CONTRIBUTORS "AS IS"
AND ANY EXPRESS OR IMPLIED WARRANTIES, INCLUDING, BUT NOT LIMITED TO, THE
IMPLIED WARRANTIES OF MERCHANTABILITY AND FITNESS FOR A PARTICULAR PURPOSE ARE
DISCLAIMED. IN NO EVENT SHALL THE COPYRIGHT HOLDER OR CONTRIBUTORS BE LIABLE
FOR ANY DIRECT, INDIRECT, INCIDENTAL, SPECIAL, EXEMPLARY, OR CONSEQUENTIAL
DAMAGES (INCLUDING, BUT NOT LIMITED TO, PROCUREMENT OF SUBSTITUTE GOODS OR
SERVICES; LOSS OF USE, DATA, OR PROFITS; OR BUSINESS INTERRUPTION) HOWEVER
CAUSED AND ON ANY THEORY OF LIABILITY, WHETHER IN CONTRACT, STRICT LIABILITY,
OR TORT (INCLUDING NEGLIGENCE OR OTHERWISE) ARISING IN ANY WAY OUT OF THE USE
OF THIS SOFTWARE, EVEN IF ADVISED OF THE POSSIBILITY OF SUCH DAMAGE.

************************************************/


//  Description   : This Module completes the packet to 60 bytes when the packets are smaller than 60 bytes

`timescale 1ns/1ps

module size_checker#
    (
        // Width of S_AXI data bus
        parameter C_AXIS_DATA_WIDTH             = 512,
        parameter TUSER_WIDTH                   =  1,
        parameter TDEST_WIDTH                   =  1

    )
    (
      (* X_INTERFACE_INFO = "xilinx.com:signal:clock:1.0 CLK CLK" *)
      (* X_INTERFACE_PARAMETER = "ASSOCIATED_BUSIF S_AXIS:M_AXIS, ASSOCIATED_RESET RST_N" *)
      input  wire                      CLK            ,
      (* X_INTERFACE_INFO = "xilinx.com:signal:reset:1.0 RST_N RST" *)
      (* X_INTERFACE_PARAMETER = "POLARITY ACTIVE_LOW" *)
      input  wire                      RST_N          ,
    
      (* X_INTERFACE_INFO = "xilinx.com:interface:axis:1.0 S_AXIS TDATA" *)  
      input  wire              [511:0] S_AXIS_TDATA   ,
      (* X_INTERFACE_INFO = "xilinx.com:interface:axis:1.0 S_AXIS TKEEP" *)
      input  wire               [63:0] S_AXIS_TKEEP   ,
      (* X_INTERFACE_INFO = "xilinx.com:interface:axis:1.0 S_AXIS TLAST" *) 
      input  wire                      S_AXIS_TLAST   ,
      (* X_INTERFACE_INFO = "xilinx.com:interface:axis:1.0 S_AXIS TVALID" *) 
      input  wire                      S_AXIS_TVALID  ,
      (* X_INTERFACE_INFO = "xilinx.com:interface:axis:1.0 S_AXIS TDEST" *) 
      input  wire  [TDEST_WIDTH-1 : 0] S_AXIS_TDEST   ,
      (* X_INTERFACE_INFO = "xilinx.com:interface:axis:1.0 S_AXIS TUSER" *) 
      input  wire  [TUSER_WIDTH-1 : 0] S_AXIS_TUSER   ,
      (* X_INTERFACE_INFO = "xilinx.com:interface:axis:1.0 S_AXIS TREADY" *) 
      output wire                      S_AXIS_TREADY  ,

      (* X_INTERFACE_INFO = "xilinx.com:interface:axis:1.0 M_AXIS TDATA" *)   
      output reg               [511:0] M_AXIS_TDATA   ,
      (* X_INTERFACE_INFO = "xilinx.com:interface:axis:1.0 M_AXIS TKEEP" *)
      output reg                [63:0] M_AXIS_TKEEP   ,
      (* X_INTERFACE_INFO = "xilinx.com:interface:axis:1.0 M_AXIS TLAST" *)
      output reg                       M_AXIS_TLAST   ,
      (* X_INTERFACE_INFO = "xilinx.com:interface:axis:1.0 M_AXIS TVALID" *)
      output reg                       M_AXIS_TVALID  ,
      (* X_INTERFACE_INFO = "xilinx.com:interface:axis:1.0 M_AXIS TDEST" *) 
      output reg   [TDEST_WIDTH-1 : 0] M_AXIS_TDEST   ,
      (* X_INTERFACE_INFO = "xilinx.com:interface:axis:1.0 M_AXIS TUSER" *)
      output reg   [TUSER_WIDTH-1 : 0] M_AXIS_TUSER   ,
      (* X_INTERFACE_INFO = "xilinx.com:interface:axis:1.0 M_AXIS TREADY" *)
      input  wire                      M_AXIS_TREADY 

);

  reg     first_transaction= 1'b1;

  assign  S_AXIS_TREADY = M_AXIS_TREADY;

  always @(*) begin
    M_AXIS_TDATA      <= S_AXIS_TDATA;    
    M_AXIS_TKEEP      <= S_AXIS_TKEEP;    
    M_AXIS_TLAST      <= S_AXIS_TLAST;    
    M_AXIS_TVALID     <= S_AXIS_TVALID;    
    M_AXIS_TDEST      <= S_AXIS_TDEST;    
    M_AXIS_TUSER      <= S_AXIS_TUSER;          

    if (S_AXIS_TVALID && S_AXIS_TLAST) begin                          // one-transaction packet
      if (first_transaction && ~S_AXIS_TKEEP[59]) begin
        M_AXIS_TKEEP    <= {4'd0,{60{1'b1}}};                         // complete packet to the minimum size (60 bytes)
      end
    end
  end


  always @(posedge CLK) begin
    if (~RST_N) begin
      first_transaction   <= 1'b1;
    end
    else begin
      if (S_AXIS_TVALID && S_AXIS_TREADY) begin                         // when a valid transaction is active tie low flag
        first_transaction   <= 1'b0;
      end

      if (S_AXIS_TVALID && S_AXIS_TREADY && S_AXIS_TLAST) begin         // one-transaction packet
        first_transaction <= 1'b1;                                      // Asserting flag with the last transaction of a packet (it could be one-transaction packet)
      end
    end
  end

endmodule

tests/size_checker_backpressure_tb.sv
`timescale 1ns/1ps

module size_checker_backpressure_tb;
  reg clk = 1'b0;
  reg rst_n = 1'b0;

  reg [511:0] s_axis_tdata = '0;
  reg [63:0] s_axis_tkeep = '0;
  reg s_axis_tlast = 1'b0;
  reg s_axis_tvalid = 1'b0;
  reg s_axis_tdest = 1'b0;
  reg s_axis_tuser = 1'b0;
  wire s_axis_tready;

  wire [511:0] m_axis_tdata;
  wire [63:0] m_axis_tkeep;
  wire m_axis_tlast;
  wire m_axis_tvalid;
  wire m_axis_tdest;
  wire m_axis_tuser;
  reg m_axis_tready = 1'b0;

  reg [579:0] stalled_payload;
  localparam [63:0] PADDED_KEEP = {4'b0000, {60{1'b1}}};

  always #5 clk = ~clk;

  size_checker dut (
    .CLK(clk),
    .RST_N(rst_n),
    .S_AXIS_TDATA(s_axis_tdata),
    .S_AXIS_TKEEP(s_axis_tkeep),
    .S_AXIS_TLAST(s_axis_tlast),
    .S_AXIS_TVALID(s_axis_tvalid),
    .S_AXIS_TDEST(s_axis_tdest),
    .S_AXIS_TUSER(s_axis_tuser),
    .S_AXIS_TREADY(s_axis_tready),
    .M_AXIS_TDATA(m_axis_tdata),
    .M_AXIS_TKEEP(m_axis_tkeep),
    .M_AXIS_TLAST(m_axis_tlast),
    .M_AXIS_TVALID(m_axis_tvalid),
    .M_AXIS_TDEST(m_axis_tdest),
    .M_AXIS_TUSER(m_axis_tuser),
    .M_AXIS_TREADY(m_axis_tready)
  );

  function automatic [579:0] output_payload;
    output_payload = {
      m_axis_tdata,
      m_axis_tkeep,
      m_axis_tlast,
      m_axis_tvalid,
      m_axis_tdest,
      m_axis_tuser
    };
  endfunction

  task automatic check_stable;
    begin
      @(posedge clk);
      #1;
      if (output_payload() !== stalled_payload)
        $fatal(1, "AXI output changed while TVALID was stalled");
    end
  endtask

  initial begin
    $dumpfile("size_checker_backpressure.vcd");
    $dumpvars(0, size_checker_backpressure_tb);

    repeat (2) @(posedge clk);
    @(negedge clk);
    rst_n = 1'b1;

    // A short single-beat frame must be padded before READY is asserted.
    s_axis_tdata = 512'h0123456789abcdef;
    s_axis_tkeep = {{44{1'b0}}, {20{1'b1}}};
    s_axis_tlast = 1'b1;
    s_axis_tvalid = 1'b1;
    s_axis_tdest = 1'b1;
    s_axis_tuser = 1'b1;
    m_axis_tready = 1'b0;

    @(posedge clk);
    #1;
    if (!m_axis_tvalid || m_axis_tkeep !== PADDED_KEEP)
      $fatal(1, "short single-beat frame was not padded while stalled");
    stalled_payload = output_payload();
    repeat (3) check_stable();

    @(negedge clk);
    m_axis_tready = 1'b1;
    @(posedge clk);
    #1;
    if (m_axis_tkeep !== PADDED_KEEP)
      $fatal(1, "padding changed on the acceptance cycle");

    // Only a single-beat frame is padded. A short final beat of a multi-beat
    // frame must keep the source mask stable during backpressure.
    @(negedge clk);
    s_axis_tdata = {512{1'b1}};
    s_axis_tkeep = {64{1'b1}};
    s_axis_tlast = 1'b0;
    @(posedge clk);

    @(negedge clk);
    s_axis_tdata = 512'hfedcba9876543210;
    s_axis_tkeep = {{54{1'b0}}, {10{1'b1}}};
    s_axis_tlast = 1'b1;
    m_axis_tready = 1'b0;
    @(posedge clk);
    #1;
    if (m_axis_tkeep !== {{54{1'b0}}, {10{1'b1}}})
      $fatal(1, "multi-beat final mask was incorrectly padded");
    stalled_payload = output_payload();
    repeat (3) check_stable();

    @(negedge clk);
    m_axis_tready = 1'b1;
    @(posedge clk);
    @(negedge clk);
    s_axis_tvalid = 1'b0;
    s_axis_tlast = 1'b0;

    $display("PASS: size_checker output is stable under backpressure");
    $finish;
  end
endmodule

tests/size_checker_backpressure.vcd
$date
	Thu Aug 27 18:48:34 2026
$end
$version
	Icarus Verilog
$end
$timescale
	1ps
$end
$scope module size_checker_backpressure_tb $end
$var wire 1 ! s_axis_tready $end
$var wire 1 " m_axis_tvalid $end
$var wire 1 # m_axis_tuser $end
$var wire 1 $ m_axis_tlast $end
$var wire 64 % m_axis_tkeep [63:0] $end
$var wire 1 & m_axis_tdest $end
$var wire 512 ' m_axis_tdata [511:0] $end
$var parameter 64 ( PADDED_KEEP $end
$var reg 1 ) clk $end
$var reg 1 * m_axis_tready $end
$var reg 1 + rst_n $end
$var reg 512 , s_axis_tdata [511:0] $end
$var reg 1 - s_axis_tdest $end
$var reg 64 . s_axis_tkeep [63:0] $end
$var reg 1 / s_axis_tlast $end
$var reg 1 0 s_axis_tuser $end
$var reg 1 1 s_axis_tvalid $end
$var reg 580 2 stalled_payload [579:0] $end
$scope function output_payload $end
$upscope $end
$scope module dut $end
$var wire 1 ) CLK $end
$var wire 1 * M_AXIS_TREADY $end
$var wire 1 + RST_N $end
$var wire 512 3 S_AXIS_TDATA [511:0] $end
$var wire 1 - S_AXIS_TDEST $end
$var wire 64 4 S_AXIS_TKEEP [63:0] $end
$var wire 1 / S_AXIS_TLAST $end
$var wire 1 ! S_AXIS_TREADY $end
$var wire 1 0 S_AXIS_TUSER $end
$var wire 1 1 S_AXIS_TVALID $end
$var parameter 32 5 C_AXIS_DATA_WIDTH $end
$var parameter 32 6 TDEST_WIDTH $end
$var parameter 32 7 TUSER_WIDTH $end
$var reg 512 8 M_AXIS_TDATA [511:0] $end
$var reg 1 & M_AXIS_TDEST $end
$var reg 64 9 M_AXIS_TKEEP [63:0] $end
$var reg 1 $ M_AXIS_TLAST $end
$var reg 1 # M_AXIS_TUSER $end
$var reg 1 " M_AXIS_TVALID $end
$var reg 1 : first_transaction $end
$upscope $end
$scope task check_stable $end
$upscope $end
$upscope $end
$enddefinitions $end
$comment Show the parameter values. $end
$dumpall
b1 7
b1 6
b1000000000 5
b111111111111111111111111111111111111111111111111111111111111 (
$end
#0
$dumpvars
1:
bx 9
bx 8
b0 4
b0 3
bx 2
01
00
0/
b0 .
0-
b0 ,
0+
0*
0)
bx '
x&
bx %
x$
x#
x"
0!
$end
#5000
1)
#10000
0)
#15000
1)
#20000
1#
1&
1"
1$
b111111111111111111111111111111111111111111111111111111111111 %
b111111111111111111111111111111111111111111111111111111111111 9
b100100011010001010110011110001001101010111100110111101111 '
b100100011010001010110011110001001101010111100110111101111 8
10
1-
11
1/
b11111111111111111111 .
b11111111111111111111 4
b100100011010001010110011110001001101010111100110111101111 ,
b100100011010001010110011110001001101010111100110111101111 3
1+
0)
#25000
1)
#26000
b10010001101000101011001111000100110101011110011011110111100001111111111111111111111111111111111111111111111111111111111111111 2
#30000
0)
#35000
1)
#40000
0)
#45000
1)
#50000
0)
#55000
1)
#60000
1!
1*
0)
#65000
b111111111111111111111111111111111111111111111111111111111111 %
b111111111111111111111111111111111111111111111111111111111111 9
1:
1)
#70000
0$
b1111111111111111111111111111111111111111111111111111111111111111 %
b1111111111111111111111111111111111111111111111111111111111111111 9
b11111111111111111111111111111111111111111111111111111111111111111111111111111111111111111111111111111111111111111111111111111111111111111111111111111111111111111111111111111111111111111111111111111111111111111111111111111111111111111111111111111111111111111111111111111111111111111111111111111111111111111111111111111111111111111111111111111111111111111111111111111111111111111111111111111111111111111111111111111111111111111111111111111111111111111111111111111111111111111111111111111111111111111111111111111111 '
b11111111111111111111111111111111111111111111111111111111111111111111111111111111111111111111111111111111111111111111111111111111111111111111111111111111111111111111111111111111111111111111111111111111111111111111111111111111111111111111111111111111111111111111111111111111111111111111111111111111111111111111111111111111111111111111111111111111111111111111111111111111111111111111111111111111111111111111111111111111111111111111111111111111111111111111111111111111111111111111111111111111111111111111111111111111 8
0/
b1111111111111111111111111111111111111111111111111111111111111111 .
b1111111111111111111111111111111111111111111111111111111111111111 4
b11111111111111111111111111111111111111111111111111111111111111111111111111111111111111111111111111111111111111111111111111111111111111111111111111111111111111111111111111111111111111111111111111111111111111111111111111111111111111111111111111111111111111111111111111111111111111111111111111111111111111111111111111111111111111111111111111111111111111111111111111111111111111111111111111111111111111111111111111111111111111111111111111111111111111111111111111111111111111111111111111111111111111111111111111111111 ,
b11111111111111111111111111111111111111111111111111111111111111111111111111111111111111111111111111111111111111111111111111111111111111111111111111111111111111111111111111111111111111111111111111111111111111111111111111111111111111111111111111111111111111111111111111111111111111111111111111111111111111111111111111111111111111111111111111111111111111111111111111111111111111111111111111111111111111111111111111111111111111111111111111111111111111111111111111111111111111111111111111111111111111111111111111111111 3
0)
#75000
0:
1)
#80000
1$
b1111111111 %
b1111111111 9
b1111111011011100101110101001100001110110010101000011001000010000 '
b1111111011011100101110101001100001110110010101000011001000010000 8
0!
0*
1/
b1111111111 .
b1111111111 4
b1111111011011100101110101001100001110110010101000011001000010000 ,
b1111111011011100101110101001100001110110010101000011001000010000 3
0)
#85000
1)
#86000
b111111101101110010111010100110000111011001010100001100100001000000000000000000000000000000000000000000000000000000000011111111111111 2
#90000
0)
#95000
1)
#100000
0)
#105000
1)
#110000
0)
#115000
1)
#120000
1!
1*
0)
#125000
b111111111111111111111111111111111111111111111111111111111111 %
b111111111111111111111111111111111111111111111111111111111111 9
1:
1)
#130000
0"
0$
b1111111111 %
b1111111111 9
0/
01
0)
